[
  {
    "employeeFullName": "Gondaliya Yash Hareshbhai",
    "mobileNumber": "9913493053",
    "department": "AI",
    "email": "yashgondaliya36@gmail.com",
    "bankName": "Bank Of Baroda - Kamrej",
    "accountHolderName": "Gondaliya Yash H",
    "bankAccountNumber": "34670100020030",
    "ifscCode": "BARB0KAMREJ"
  },
  {
    "employeeFullName": "Aditya Shrivastav Sanjay",
    "mobileNumber": "9574661174",
    "department": "AI",
    "email": "adityashrivastav942@gmail.com",
    "bankName": "IDFC FIRST",
    "accountHolderName": "Shrivastav Aditya",
    "bankAccountNumber": "10234104862",
    "ifscCode": "IDFB0042262"
  },
  {
    "employeeFullName": "Jasmin Kachhadiya",
    "mobileNumber": "7801819724",
    "department": "Digital Marketing",
    "email": "kachhadiyajasmin2@gmail.com",
    "bankName": "Axis Bank",
    "accountHolderName": "KACHADIYA JASMIN MAHESHBHAI",
    "bankAccountNumber": "921010032560443",
    "ifscCode": "UTIB0002360"
  },
  {
    "employeeFullName": "rudra sonani",
    "mobileNumber": "9725483165",
    "department": "Digital Marketing",
    "email": "rudrasonani40@gmail.com",
    "bankName": "KOTAK",
    "accountHolderName": "Sonani Rudra Hareshbhai",
    "bankAccountNumber": "8348093678",
    "ifscCode": "KKBK0002868"
  },
  {
    "employeeFullName": "Khyati Bhut",
    "mobileNumber": "9978770119",
    "department": "Web",
    "email": "khyatibhut2822@gmail.com",
    "bankName": "HDFC BANK",
    "accountHolderName": "BHUT KHYATI PARESHBHAI",
    "bankAccountNumber": "50100546292514",
    "ifscCode": "HDFC0004693"
  },
  {
    "employeeFullName": "rutika savaliya",
    "mobileNumber": "9265737311",
    "department": "Graphic",
    "email": "savaliyarutika967@gmail.com",
    "bankName": "kotak Bank",
    "accountHolderName": "savaliya Rutika Mahendrabhai",
    "bankAccountNumber": "1649227803",
    "ifscCode": "KKBK0002865"
  },
  {
    "employeeFullName": "Kaushik Vaghasiya",
    "mobileNumber": "6353125194",
    "department": "Web",
    "email": "kaushikvaghasiya605@gmail.com",
    "bankName": "BOB",
    "accountHolderName": "VAGHASIYA KAUSHIK BALVANTBHAI",
    "bankAccountNumber": "34670100018863",
    "ifscCode": "BARB0KAMREJ"
  },
  {
    "employeeFullName": "RUPESH GARSONDIYA PANKAJBHAI",
    "mobileNumber": "9904758150",
    "department": "AI",
    "email": "rupeshgarsondiya38@gmail.com",
    "bankName": "IDBI",
    "accountHolderName": "GARSONDIYA RUPESH PANKAJBHAI",
    "bankAccountNumber": "20063280814051",
    "ifscCode": "IBKL0002037"
  },
  {
    "employeeFullName": "Solanki Keval Sharadbhai",
    "mobileNumber": "8347066732",
    "department": "AI",
    "email": "work.keval.solanki@gmail.com",
    "bankName": "Axis Bank",
    "accountHolderName": "Solanki Keval Sharadbhai",
    "bankAccountNumber": "925010010293109",
    "ifscCode": "UTIB0001037"
  },
  {
    "employeeFullName": "Narendra Govindbhai Mali",
    "mobileNumber": "7874748401",
    "department": "Web",
    "email": "narendramali7874@gmail.com",
    "bankName": "SBI",
    "accountHolderName": "Narendra Govindbhai Mali",
    "bankAccountNumber": "41362767244",
    "ifscCode": "SBIN0018698"
  },
  {
    "employeeFullName": "Tushar Sutariya",
    "mobileNumber": "8780805275",
    "department": "Digital Marketing",
    "email": "sutariyatushar41@gmail.com",
    "bankName": "State Bank Of India",
    "accountHolderName": "TUSHAR RAJUBHAI SUTARIYA",
    "bankAccountNumber": "35867687951",
    "ifscCode": "SBIN0060019"
  },
  {
    "employeeFullName": "Thakur Prashantkumar Radhakrishna",
    "mobileNumber": "9737901133",
    "department": "AI",
    "email": "tprashant1729@gmail.com",
    "bankName": "Kotak Mahindra Bank",
    "accountHolderName": "Thakur Prashantkumar Radhakrishna",
    "bankAccountNumber": "0645593219",
    "ifscCode": "KKBK0002849"
  },
  {
    "employeeFullName": "Bhargav Kikani",
    "mobileNumber": "7069135299",
    "department": "Web",
    "email": "bhargavkikani9999@gmail.com",
    "bankName": "State Bank of India",
    "accountHolderName": "Mr. BHARAGAV BHARATBHAI KIKANI",
    "bankAccountNumber": "32983376669",
    "ifscCode": "SBIN0060308"
  },
  {
    "employeeFullName": "patel harsh vinodbhai",
    "mobileNumber": "9157752911",
    "department": "AI",
    "email": "hp333854@gmail.com",
    "bankName": "SBI",
    "accountHolderName": "Mr. Patel Harsh",
    "bankAccountNumber": "41302422175",
    "ifscCode": "SBIN0012700"
  },
  {
    "employeeFullName": "Jenish Bravaliya",
    "mobileNumber": "9510007247",
    "department": "AI",
    "email": "jenishbarvaliya2012@gmail.com",
    "bankName": "Bank Of Baroda",
    "accountHolderName": "jenish varsantbhai barvaliya",
    "bankAccountNumber": "34670100012873",
    "ifscCode": "BARB0KAMREJ"
  },
  {
    "employeeFullName": "Nasit Jemil Bharatbhai",
    "mobileNumber": "9157455704",
    "department": "AI",
    "email": "jemilnasit5@gmail.com",
    "bankName": "SBI",
    "accountHolderName": "NASIT JEMIL BHARATBHAI",
    "bankAccountNumber": "36716522407",
    "ifscCode": "SBIN0013359"
  },
  {
    "employeeFullName": "Khanakh Prajapati",
    "mobileNumber": "9313212890",
    "department": "AI",
    "email": "khanakhjp@gmail.com",
    "bankName": "ICICI",
    "accountHolderName": "Khanakh Prajapati",
    "bankAccountNumber": "777701558531",
    "ifscCode": "ICIC0002130"
  },
  {
    "employeeFullName": "Himanshi Maheshbhai Patel",
    "mobileNumber": "8200773061",
    "department": "AI",
    "email": "phimanshi009@gmail.com",
    "bankName": "Bank of baroda",
    "accountHolderName": "PATEL HIMANSHI MAHESHBHAI",
    "bankAccountNumber": "35640100023630",
    "ifscCode": "BARB0PUNSUR"
  },
  {
    "employeeFullName": "kalariya hit",
    "mobileNumber": "6352617754",
    "department": "AI",
    "email": "hitkalariya88@gmail.com",
    "bankName": "surat peoples co.",
    "accountHolderName": "kalariya hit prakashbhai",
    "bankAccountNumber": "304021314892",
    "ifscCode": "SPCB0251014"
  },
  {
    "employeeFullName": "Praduman Kumar",
    "mobileNumber": "9117446581",
    "department": "Web",
    "email": "praduman802213@gmail.com",
    "bankName": "Punjab National Bank",
    "accountHolderName": "Praduman Kumar",
    "bankAccountNumber": "1689001700109916",
    "ifscCode": "PUNB0168900"
  },
  {
    "employeeFullName": "maulik jaysukhbhai ghoghari",
    "mobileNumber": "6351260524",
    "department": "Web",
    "email": "maulikghoghari20@gmail.com",
    "bankName": "the varachha co-operative bank ltd",
    "accountHolderName": "maulik jaysukhbhai ghoghari",
    "bankAccountNumber": "00610120574522",
    "ifscCode": "VARA0289006"
  },
  {
    "employeeFullName": "Bhadani Arshit Mansukhbhai",
    "mobileNumber": "7359176361",
    "department": "Digital Marketing",
    "email": "arshitbhadani1210@gmail.com",
    "bankName": "HDFC Bank",
    "accountHolderName": "Bhadani Arshit Mansukhbhai",
    "bankAccountNumber": "50100866018232",
    "ifscCode": "HDFC0005894"
  },
  {
    "employeeFullName": "Arvind Yadav",
    "mobileNumber": "8154885803",
    "department": "Digital Marketing",
    "email": "arvindyadav11436@gmail.com",
    "bankName": "STATE BANK OF INDIA",
    "accountHolderName": "YADAV ARVIND YADAV",
    "bankAccountNumber": "35202249776",
    "ifscCode": "SBIN0011244"
  }
]